{"nodes": [{"id": "e2e_export_spec_ts", "label": "export.spec.ts", "file_type": "code", "source_file": "e2e/export.spec.ts", "source_location": "L1"}, {"id": "export_spec_setupauth", "label": "setupAuth()", "file_type": "code", "source_file": "e2e/export.spec.ts", "source_location": "L40"}, {"id": "export_spec_mockcontentflow", "label": "mockContentFlow()", "file_type": "code", "source_file": "e2e/export.spec.ts", "source_location": "L69"}, {"id": "export_spec_generatecontentandwaitforexportbar", "label": "generateContentAndWaitForExportBar()", "file_type": "code", "source_file": "e2e/export.spec.ts", "source_location": "L133"}], "edges": [{"source": "e2e_export_spec_ts", "target": "test", "relation": "imports_from", "confidence": "EXTRACTED", "source_file": "e2e/export.spec.ts", "source_location": "L25", "weight": 1.0}, {"source": "e2e_export_spec_ts", "target": "export_spec_setupauth", "relation": "contains", "confidence": "EXTRACTED", "source_file": "e2e/export.spec.ts", "source_location": "L40", "weight": 1.0}, {"source": "e2e_export_spec_ts", "target": "export_spec_mockcontentflow", "relation": "contains", "confidence": "EXTRACTED", "source_file": "e2e/export.spec.ts", "source_location": "L69", "weight": 1.0}, {"source": "e2e_export_spec_ts", "target": "export_spec_generatecontentandwaitforexportbar", "relation": "contains", "confidence": "EXTRACTED", "source_file": "e2e/export.spec.ts", "source_location": "L133", "weight": 1.0}], "raw_calls": [{"caller_nid": "export_spec_setupauth", "callee": "goto", "source_file": "e2e/export.spec.ts", "source_location": "L41"}, {"caller_nid": "export_spec_setupauth", "callee": "evaluate", "source_file": "e2e/export.spec.ts", "source_location": "L42"}, {"caller_nid": "export_spec_setupauth", "callee": "route", "source_file": "e2e/export.spec.ts", "source_location": "L46"}, {"caller_nid": "export_spec_mockcontentflow", "callee": "route", "source_file": "e2e/export.spec.ts", "source_location": "L71"}, {"caller_nid": "export_spec_mockcontentflow", "callee": "route", "source_file": "e2e/export.spec.ts", "source_location": "L80"}, {"caller_nid": "export_spec_mockcontentflow", "callee": "route", "source_file": "e2e/export.spec.ts", "source_location": "L101"}, {"caller_nid": "export_spec_mockcontentflow", "callee": "route", "source_file": "e2e/export.spec.ts", "source_location": "L110"}, {"caller_nid": "export_spec_generatecontentandwaitforexportbar", "callee": "goto", "source_file": "e2e/export.spec.ts", "source_location": "L137"}, {"caller_nid": "export_spec_generatecontentandwaitforexportbar", "callee": "waitForSelector", "source_file": "e2e/export.spec.ts", "source_location": "L138"}, {"caller_nid": "export_spec_generatecontentandwaitforexportbar", "callee": "fill", "source_file": "e2e/export.spec.ts", "source_location": "L141"}, {"caller_nid": "export_spec_generatecontentandwaitforexportbar", "callee": "locator", "source_file": "e2e/export.spec.ts", "source_location": "L141"}, {"caller_nid": "export_spec_generatecontentandwaitforexportbar", "callee": "all", "source_file": "e2e/export.spec.ts", "source_location": "L146"}, {"caller_nid": "export_spec_generatecontentandwaitforexportbar", "callee": "waitForResponse", "source_file": "e2e/export.spec.ts", "source_location": "L147"}, {"caller_nid": "export_spec_generatecontentandwaitforexportbar", "callee": "click", "source_file": "e2e/export.spec.ts", "source_location": "L151"}, {"caller_nid": "export_spec_generatecontentandwaitforexportbar", "callee": "locator", "source_file": "e2e/export.spec.ts", "source_location": "L151"}, {"caller_nid": "export_spec_generatecontentandwaitforexportbar", "callee": "status", "source_file": "e2e/export.spec.ts", "source_location": "L155"}, {"caller_nid": "export_spec_generatecontentandwaitforexportbar", "callee": "status", "source_file": "e2e/export.spec.ts", "source_location": "L156"}, {"caller_nid": "export_spec_generatecontentandwaitforexportbar", "callee": "waitFor", "source_file": "e2e/export.spec.ts", "source_location": "L160"}, {"caller_nid": "export_spec_generatecontentandwaitforexportbar", "callee": "locator", "source_file": "e2e/export.spec.ts", "source_location": "L160"}]}