{"nodes": [{"id": "frontend_src_pages_termsofservice_jsx", "label": "TermsOfService.jsx", "file_type": "code", "source_file": "frontend/src/pages/TermsOfService.jsx", "source_location": "L1"}, {"id": "termsofservice_termsofservice", "label": "TermsOfService()", "file_type": "code", "source_file": "frontend/src/pages/TermsOfService.jsx", "source_location": "L5"}], "edges": [{"source": "frontend_src_pages_termsofservice_jsx", "target": "react", "relation": "imports_from", "confidence": "EXTRACTED", "source_file": "frontend/src/pages/TermsOfService.jsx", "source_location": "L1", "weight": 1.0}, {"source": "frontend_src_pages_termsofservice_jsx", "target": "react_router_dom", "relation": "imports_from", "confidence": "EXTRACTED", "source_file": "frontend/src/pages/TermsOfService.jsx", "source_location": "L2", "weight": 1.0}, {"source": "frontend_src_pages_termsofservice_jsx", "target": "lucide_react", "relation": "imports_from", "confidence": "EXTRACTED", "source_file": "frontend/src/pages/TermsOfService.jsx", "source_location": "L3", "weight": 1.0}, {"source": "frontend_src_pages_termsofservice_jsx", "target": "termsofservice_termsofservice", "relation": "contains", "confidence": "EXTRACTED", "source_file": "frontend/src/pages/TermsOfService.jsx", "source_location": "L5", "weight": 1.0}], "raw_calls": [{"caller_nid": "termsofservice_termsofservice", "callee": "useEffect", "source_file": "frontend/src/pages/TermsOfService.jsx", "source_location": "L6"}]}